__init__.py
analysta_llm_agents/__init__.py
analysta_llm_agents/agent/__init__.py
analysta_llm_agents/agent/agent.py
analysta_llm_agents/agent/base_tools.py
analysta_llm_agents/agent/defaults.py
analysta_llm_agents/agent/memory.py
analysta_llm_agents/base/__init__.py
analysta_llm_agents/base/agent.py
analysta_llm_agents/master/__init__.py
analysta_llm_agents/master/agent.py
analysta_llm_agents/master/constants.py
analysta_llm_agents/rag/__init__.py
analysta_llm_agents/rag/agent.py
analysta_llm_agents/rag/constants.py
analysta_llm_agents/react/__init__.py
analysta_llm_agents/react/agent.py
analysta_llm_agents/react/base_commands.py
analysta_llm_agents/react/constants.py
analysta_llm_agents/tools/__init__.py
analysta_llm_agents/tools/context.py
analysta_llm_agents/tools/tool.py
analysta_llm_agents/tools/utils.py
analysta_llm_agents/tools/retrievers/AgentBasedRetriever.py
analysta_llm_agents-0.3.0.dist-info/LICENSE
analysta_llm_agents-0.3.0.dist-info/METADATA
analysta_llm_agents-0.3.0.dist-info/WHEEL
analysta_llm_agents-0.3.0.dist-info/top_level.txt
analysta_llm_agents-0.3.0.dist-info/RECORD
