Metadata-Version: 2.1
Name: analysta_llm_agents
Version: 0.3.0
Summary: LLM Agents library to build single-shot, react and master agents
Author-email: Artem Rozumenko <support@analysta.ai>
Project-URL: Homepage, https://analysta.ai
Project-URL: Issues, https://github.com/analysta-ai/llm-agents/issues
Classifier: Programming Language :: Python :: 3
Classifier: License :: OSI Approved :: Apache Software License
Classifier: Operating System :: OS Independent
Requires-Python: >=3.7
License-File: LICENSE
Requires-Dist: openai ==1.3.7
Requires-Dist: tiktoken ==0.5.2
Requires-Dist: urllib3 ==2.1.0
Requires-Dist: jsonpath-ng ==1.6.1
Requires-Dist: analysta-index ==0.2.9
